PrimeNumber/__init__.py
PrimeNumber/file_prime.py
PrimeNumber-2.0.1.dist-info/LICENSE
PrimeNumber-2.0.1.dist-info/METADATA
PrimeNumber-2.0.1.dist-info/WHEEL
PrimeNumber-2.0.1.dist-info/top_level.txt
PrimeNumber-2.0.1.dist-info/RECORD
